[
    { "id": "010011.IB", "name": "国债组合", "updated": "2018-08-20" },
    { "id": "010012.IB", "name": "又一个国债组合", "updated": "2018-08-20" },
    { "id": "010013.IB", "name": "还是国债组合", "updated": "2018-08-20" },
    { "id": "010011.IB", "name": "11年国债", "updated": "2018-08-20" },
    { "id": "010012.IB", "name": "又一个国债组合", "updated": "2018-08-20" },
    { "id": "010013.IB", "name": "13年国债", "updated": "2018-08-20" },
    { "id": "010011.IB", "name": "11年国债", "updated": "2018-08-20" },
    { "id": "010012.IB", "name": "又一个国债组合", "updated": "2018-08-20" },
    { "id": "010013.IB", "name": "13年国债", "updated": "2018-08-20" },
    { "id": "010011.IB", "name": "11年国债", "updated": "2018-08-20" },
    { "id": "010012.IB", "name": "又一个国债组合", "updated": "2018-08-20" },
    { "id": "010013.IB", "name": "13年国债", "updated": "2018-08-20" },
    { "id": "010011.IB", "name": "11年国债", "updated": "2018-08-20" },
    { "id": "010012.IB", "name": "又一个国债组合", "updated": "2018-08-20" },
    { "id": "010013.IB", "name": "13年国债", "updated": "2018-08-20" },
    { "id": "010011.IB", "name": "11年国债", "updated": "2018-08-20" },
    { "id": "010012.IB", "name": "又一个国债组合", "updated": "2018-08-20" },
    { "id": "010013.IB", "name": "13年国债", "updated": "2018-08-20" },
    { "id": "010011.IB", "name": "11年国债", "updated": "2018-08-20" },
    { "id": "010012.IB", "name": "又一个国债组合", "updated": "2018-08-20" },
    { "id": "010013.IB", "name": "13年国债", "updated": "2018-08-20" },
    { "id": "010011.IB", "name": "11年国债", "updated": "2018-08-20" },
    { "id": "010012.IB", "name": "又一个国债组合", "updated": "2018-08-20" },
    { "id": "010013.IB", "name": "13年国债", "updated": "2018-08-20" },
    { "id": "010011.IB", "name": "11年国债", "updated": "2018-08-20" },
    { "id": "010012.IB", "name": "又一个国债组合", "updated": "2018-08-20" },
    { "id": "010013.IB", "name": "13年国债", "updated": "2018-08-20" }
]
